simplezfs/__init__.py
simplezfs/exceptions.py
simplezfs/pe_helper.py
simplezfs/py.typed
simplezfs/types.py
simplezfs/validation.py
simplezfs/zfs.py
simplezfs/zfs_cli.py
simplezfs/zfs_native.py
simplezfs/zpool.py
simplezfs/zpool_cli.py
simplezfs/zpool_native.py
simplezfs-0.0.3.dist-info/LICENSE
simplezfs-0.0.3.dist-info/METADATA
simplezfs-0.0.3.dist-info/WHEEL
simplezfs-0.0.3.dist-info/top_level.txt
simplezfs-0.0.3.dist-info/RECORD
