Metadata-Version: 2.1
Name: simplezfs
Version: 0.0.3
Summary: Simple, low-level ZFS API
Home-page: https://github.com/svalouch/python-simplezfs
Author: Stefan Valouch
Author-email: svalouch@valouch.com
License: BSD-3-Clause
Project-URL: Documentation, https://simplezfs.readthedocs.io/
Project-URL: Source, https://github.com/svalouch/python-simplezfs/
Project-URL: Tracker, https://github.com/svalouch/python-simplezfs/issues
Platform: any
Classifier: Development Status :: 2 - Pre-Alpha
Classifier: License :: OSI Approved :: BSD License
Classifier: Operating System :: POSIX :: Linux
Classifier: Programming Language :: Python
Classifier: Programming Language :: Python :: 3
Classifier: Programming Language :: Python :: 3 :: Only
Classifier: Programming Language :: Python :: 3.6
Classifier: Programming Language :: Python :: 3.7
Classifier: Programming Language :: Python :: 3.8
Classifier: Programming Language :: Python :: 3.9
Requires-Python: >=3.6
License-File: LICENSE
Requires-Dist: typing-extensions ; python_version < "3.8"
Provides-Extra: docs
Requires-Dist: Sphinx (>=2.0) ; extra == 'docs'
Requires-Dist: sphinx-autodoc-typehints ; extra == 'docs'
Requires-Dist: sphinx-rtd-theme ; extra == 'docs'
Requires-Dist: recommonmark (>=0.5.0) ; extra == 'docs'
Provides-Extra: tests
Requires-Dist: mypy ; extra == 'tests'
Requires-Dist: pylint ; extra == 'tests'
Requires-Dist: pytest ; extra == 'tests'
Requires-Dist: pytest-cov ; extra == 'tests'
Requires-Dist: pytest-pylint ; extra == 'tests'
